{
    "stems": [

  {
    "text": "The following table compares the heights of students in a class at a primary school. One student was absent on the day the heights were recorded.",
    "image": "https://in2med.com.au/wp-content/uploads/2021/01/Question Images (Upload)/QR Images/Questions/Centre & Spread/Batch 2 (Sahil)/1.JPG",
    "category_id": 11,
    "questions": [

  {
    "text": "What was the average height of the students whose heights were recorded?",
        "type": "Multiple Choice",
        "options": [
          "101.8cm",
          "113.4cm",
          "116.3cm",
          "117.4cm"
        ],
        "answer": "C",
        "explanation": "Add the heights up and divide by 7",
        "difficulty": 1
      }
    ]
  },

  {
    "text": "What was Tim’s height if the average height of the students in the class was 118cm?",
        "type": "Multiple Choice",
        "options": [
          "123.8cm",
          "125.5cm",
          "128.4cm",
          "129.6cm"
        ],
        "answer": "D",
        "explanation": "118 * 8 – sum of 7 other heights (814.4) = 129.6",
        "difficulty": 1
      }
    ]
  },

  {
    "text": "If Tim is taller than Liam but smaller than May, what is the range of heights of students in the class?",
        "type": "Multiple Choice",
        "options": [
          "12.8cm",
          "13.1cm",
          "14.5cm",
          "Can’t tell (as Liam’s height is not provided)"
        ],
        "answer": "C",
        "explanation": "121.3 – 106.8 = 14.5",
        "difficulty": 1
      }
    ]
  },

  {
    "text": "If Tim’s height is 5cm greater than the average height of the 8 students, what is Tim’s height?",
        "type": "Multiple Choice",
        "options": [
          "120.7cm",
          "121.3cm",
          "122.1cm",
          "123.0cm"
        ],
        "answer": "C",
        "explanation": "(Sum of heights + x)/8 = x – 5; x = 122.1",

        "difficulty": 1
      }
    ]
  },

  {
    "text": "The table below illustrates the number of paying customers and the total number of items purchased (in thousands) at a large retailer from January to December 2019. Suppose that the average cost of items purchased at the shopping centre was $21.47 every month of 2019. ",
    "image": "https://in2med.com.au/wp-content/uploads/2021/01/Question Images (Upload)/QR Images/Questions/Centre & Spread/Batch 2 (Sahil)/2.JPG",
    "category_id": 11,
    "questions": [

  {
    "text": "What was the average number of items purchased from the retailer each month for 2019 (in thousands)?",
        "type": "Multiple Choice",
        "options": [
          "39",
          "39.5",
          "40",
          "40.5"
        ],
        "answer": "B",
        "explanation": "Add the entries up (in the total items purchased column) and divide by 12 ",
        "difficulty": 1
      }
    ]
  },

  {
    "text": "If the average number of items purchased each month increased by 20% from 2018 to 2019, how many more items were purchased from the retailer in 2019 than 2018 (in thousands)?",
        "type": "Multiple Choice",
        "options": [
          "6.58 ",
          "7.90",
          "78.97",
          "94.77"
        ],
        "answer": "C",
        "explanation": "39.5 – 39.5/1.2 = 6.6; 6.6 * 12 = ~79",
        "difficulty": 1
      }
    ]
  },

  {
    "text": "What was the average amount spent by each customer on items in January and February 2019?",
        "type": "Multiple Choice",
        "options": [
          "$3.14",
          "$20.47",
          "$45.25",
          "$67.52"
        ],
        "answer": "D",
        "explanation": "(38.61 + 42.27)/(12.34 + 13.38) * 21.47 = $67.52",
        "difficulty": 1
      }
    ]
  },

  {
    "text": "All of the money generated by the retailer comes from the items sold. If 30% of the money generated is spent on tax, 30% is expenses and the rest is profit, what was the retailer’s average monthly profit for 2019 (to the nearest $1000)?",
        "type": "Multiple Choice",
        "options": [
          "$3000",
          "$39,000",
          "$339,000",
          "$3,339,000"
        ],
        "answer": "C",
        "explanation": "39.5 * 21.47 * 0.4 = 339 (K)",

        "difficulty": 1
      }
    ]
  },

  {
    "text": "The exam scores of students from a year 10 class in mathematics, physics and chemistry are recorded below. If a student scores less than 50 in an exam, they are asked to re-sit their exam and their original mark is changed to their re-sit mark.",
    "image": "https://in2med.com.au/wp-content/uploads/2021/01/Question Images (Upload)/QR Images/Questions/Centre & Spread/Batch 2 (Sahil)/3.JPG",
    "category_id": 11,
    "questions": [

  {
    "text": "What was the average chemistry exam score in the class (not considering re-sits)?",
        "type": "Multiple Choice",
        "options": [
          "74.5",
          "77.7",
          "79.4",
          "81.1"
        ],
        "answer": "D",
        "explanation": "Sum of all the chemistry scores/10 = 81.1",
        "difficulty": 1
      }
    ]
  },

  {
    "text": "How much higher was the average mathematics score than the average physics score (not considering re-sits)? ",
        "type": "Multiple Choice",
        "options": [
          "4.8",
          "5.3",
          "6.9",
          "7.4"
        ],
        "answer": "B",
        "explanation": "Sum of all the mathematics scores/10 – sum of all the physics scores/10 = 5.3",
        "difficulty": 1
      }
    ]
  },

  {
    "text": "If the individual(s) re-sitting their chemistry exam score(s) twice as high when re-sitting, by how much will the average chemistry score increase?",
        "type": "Multiple Choice",
        "options": [
          "3.8",
          "4.8",
          "7.8",
          "8.8"
        ],
        "answer": "A",
        "explanation": "38/10 = 3.8 ",
        "difficulty": 1
      }
    ]
  },

  {
    "text": "After adjusting the physics exam marks (after re-sits), the average physics mark increased to 75.9. What was the average final mark of those who re-sat the physics exam?",
        "type": "Multiple Choice",
        "options": [
          "35",
          "61",
          "70",
          "76"
        ],
        "answer": "B",
        "explanation": "75.9 * 10 – sum of scores of those who passed = 122; 122/2 = 61",

        "difficulty": 1
      }
    ]
  },

  {
    "text": "Ryan, a long-distance runner, went on 6 separate runs in preparation for an upcoming competition.He gradually increased the time he spent on each run and the distance. Times are expressed as hours: minutes: seconds and all distances are in miles.",
    "image": "https://in2med.com.au/wp-content/uploads/2021/01/Question Images (Upload)/QR Images/Questions/Centre & Spread/Batch 2 (Sahil)/4.JPG",
    "category_id": 11,
    "questions": [

  {
    "text": "What was the average distance of the 5 runs (with distance indicated) in miles?",
        "type": "Multiple Choice",
        "options": [
          "38.3",
          "40.2",
          "43.8",
          "46.0"
        ],
        "answer": "D",
        "explanation": "Sum of 5 runs/5 = 46.0",
        "difficulty": 1
      }
    ]
  },

  {
    "text": "If the average distance of the 6 runs was 15% lower than the average distance of the 5 runs (with distance indicated), what was the distance of the first run?",
        "type": "Multiple Choice",
        "options": [
          "4.6",
          "5.0",
          "5.4",
          "5.8"
        ],
        "answer": "A",
        "explanation": "46.0 * 0.85 * 6 – sum of 5 runs = 4.6",
        "difficulty": 1
      }
    ]
  },

  {
    "text": "If the average speed of the first run was 6 miles per hour, what was the distance of the first run?",
        "type": "Multiple Choice",
        "options": [
          "11.63",
          "11.64",
          "11.65",
          "11.66"
        ],
        "answer": "C",
        "explanation": "6 * (1 + 56/60 + 27/3600) = 11.65",
        "difficulty": 1
      }
    ]
  },

  {
    "text": "If the average speed of the first run was 6 miles per hour, which run did Ryan travel at the fastest average speed?",
        "type": "Multiple Choice",
        "options": [
          "First run",
          "Second run ",
          "Fourth run",
          "Fifth run"
        ],
        "answer": "D",
        "explanation": "Can attempt to calculate average speeds (distance/time) or use a method of inspection and estimation (preferable to maximise time efficiency)",

        "difficulty": 1
      }
    ]
  },

  {
    "text": "The following table illustrates the amount spent and earned by Chris, a high school student working shifts at the local bakery, over the course of one and a half weeks. He does not have to pay tax on any amount earned.",
    "image": "https://in2med.com.au/wp-content/uploads/2021/01/Question Images (Upload)/QR Images/Questions/Centre & Spread/Batch 2 (Sahil)/5.JPG",
    "category_id": 11,
    "questions": [

  {
    "text": "What was the average amount spent by Chris (per day) over the days given (to the nearest dollar)? ",
        "type": "Multiple Choice",
        "options": [
          "$38",
          "$39",
          "$40",
          "$41"
        ],
        "answer": "B",
        "explanation": "Total amount spent/11 = ~39 ",
        "difficulty": 1
      }
    ]
  },

  {
    "text": "If Chris’ hourly rates are twice as high on weekends than weekdays, how much longer did he work on the first Friday compared to Saturday?",
        "type": "Multiple Choice",
        "options": [
          "1.25 times as long",
          "Twice as long",
          "2.5 times as long",
          "Can’t tell (hourly rate required)"
        ],
        "answer": "C",
        "explanation": "40/2 = 20; 50/20 = 2.5",
        "difficulty": 1
      }
    ]
  },

  {
    "text": "Suppose that Chris transfers all the money he earns (minus the money he spends) to his bank account every day. If he spends more money than he earns on a given day, he must withdraw the gap from his bank account. What is the average amount Chris transfers/ withdraws from his account every day over the period given?",
        "type": "Multiple Choice",
        "options": [
          "Transfers $1.91",
          "Transfers $2.50",
          "Withdraws $1.91",
          "Withdraws $2.50"
        ],
        "answer": "A",
        "explanation": "(Sum of money earnt – sum of money spent)/11 = 1.91",
        "difficulty": 1
      }
    ]
  },

  {
    "text": "Chris decides to save up for a $5000 car. Over the course of a year, he earns the same amount (daily) as the average amount in the table above and reduces his spending to 20% of his earnings. How long (to the nearest 10 days) will it take Chris to save up the $5000 for the car?",
        "type": "Multiple Choice",
        "options": [
          "110 days",
          "130 days",
          "150 days",
          "170 days"
        ],
        "answer": "C",
        "explanation": "Average earnt = sum/11 = 41.1; 41.4 * 0.8 = 33; 5000/33 = ~150",

        "difficulty": 1
      }
    ]
  },

  {
    "text": "Over the year, there are 7 different assessment pieces for chemistry. The assessments each have a different weighting in contributing to the student’s overall score. The results of one student in chemistry is given below.",
    "image": "https://in2med.com.au/wp-content/uploads/2021/01/Question Images (Upload)/QR Images/Questions/Centre & Spread/Batch 2 (Sahil)/6.JPG",
    "category_id": 11,
    "questions": [

  {
    "text": "What was the average mark achieved by the student in the assessments (not the weighted average)?",
        "type": "Multiple Choice",
        "options": [
          "76.1",
          "79.5",
          "80.1",
          "82.5"
        ],
        "answer": "C",
        "explanation": "Sum of the marks/7 = 80.1",
        "difficulty": 1
      }
    ]
  },

  {
    "text": "What was the student’s overall score (i.e/ the weighted average mark)?",
        "type": "Multiple Choice",
        "options": [
          "76.6",
          "77.7",
          "78.8",
          "79.9"
        ],
        "answer": "A",
        "explanation": "Weightage/100 * mark for assignment 1 + Weightage/100 * mark for assignment 2… = 76.6",
        "difficulty": 1
      }
    ]
  },

  {
    "text": "How much higher did the student have to score on the exam in order to achieve an overall score of 80?",
        "type": "Multiple Choice",
        "options": [
          "6",
          "7",
          "8",
          "9"
        ],
        "answer": "D",
        "explanation": "80 – 76.6 =3.4; 3.4/0.4 = 9",
        "difficulty": 1
      }
    ]
  },

  {
    "text": "If the weightage of the exam was halved and quiz 2 tripled, what would be the percentage increase in the student’s overall score?",
        "type": "Multiple Choice",
        "options": [
          "2.2%",
          "3.3%",
          "4.4%",
          "5.5%"
        ],
        "answer": "C",
        "explanation": "Weightage/100 * mark for assignment 1 + Weightage/100 * mark for assignment 2… (using the weightage for the exam as 20 and quiz 2 as 30)= ~80; (80 – 76.6)/76.6 * 100 = 4.4",


        "difficulty": 1
      }
    ]
  },

  {
    "text": "Erin, Lisa, Molly, Joseph and Brian competitively played 3 games of bowling and their scores were recorded. The scores are displayed on the table below. The individual with the highest average score wins the 1st prize of $60, the individual with the second average score wins the 2nd prize of $30 and the individual with the third highest average score wins the 3rd prize of $20.",
    "image": "https://in2med.com.au/wp-content/uploads/2021/01/Question Images (Upload)/QR Images/Questions/Centre & Spread/Batch 2 (Sahil)/7.JPG",
    "category_id": 11,
    "questions": [

  {
    "text": "Who won the bowling competition?",
        "type": "Multiple Choice",
        "options": [
          "Erin",
          "Lisa",
          "Molly",
          "Joseph"
        ],
        "answer": "D",
        "explanation": "Calculate the averages for each to determine who had the highest average (sum the 3 games and divide by 3) or determine the answer by inspection. Joseph had the highest average of 105",
        "difficulty": 1
      }
    ]
  },

  {
    "text": "How much more money did Lisa win than Brian?",
        "type": "Multiple Choice",
        "options": [
          "$10",
          "$20",
          "$30",
          "$60"
        ],
        "answer": "C",
        "explanation": "Lisa came second ($30) and Brian was not in the top 3",
        "difficulty": 1
      }
    ]
  },

  {
    "text": "In the case of a draw for a prize, those who are drawn are required to have another game. Which 2 competitors   ",
        "type": "Multiple Choice",
        "options": [
          "Lisa and Brian",
          "Molly and Brian",
          "Erin and Molly",
          "Erin and Brian"
        ],
        "answer": "C",
        "explanation": "Both Erin and Molly had an average of: (76 + 96 + 120)/3 = 97.3",
        "difficulty": 1
      }
    ]
  },

  {
    "text": "Jill also joins in the competition and achieves the same bowling score in 3 consecutive games. What percentage increase in her 3rd throw will yield a 10% increase in her average score?",
        "type": "Multiple Choice",
        "options": [
          "10%",
          "30%",
          "33%",
          "Can’t tell"
        ],
        "answer": "B",
        "explanation": "10 * 3 = 30",

        "difficulty": 1
      }
    ]
  },

  {
    "text": "The following table displays the hours worked per week and the hourly rate of 11 friends. A tax rate of 10% is applied to the first $500 of money generated each week and a tax rate of 20% applies to any money in excess of $500 generated in a week. Whatever is left over after tax is the individual’s income.",
    "image": "https://in2med.com.au/wp-content/uploads/2021/01/Question Images (Upload)/QR Images/Questions/Centre & Spread/Batch 2 (Sahil)/8.JPG",
    "category_id": 11,
    "questions": [

  {
    "text": "What was the average number of hours worked per week by the 11 friends?",
        "type": "Multiple Choice",
        "options": [
          "25",
          "30",
          "35",
          "40"
        ],
        "answer": "C",
        "explanation": "Sum of hours/11 = 35",
        "difficulty": 1
      }
    ]
  },

  {
    "text": "What was the average amount of money generated (per week) by the 3 individuals with the lowest weekly income?",
        "type": "Multiple Choice",
        "options": [
          "$405",
          "$425",
          "$455",
          "$500"
        ],
        "answer": "A",
        "explanation": "Stanley, Jenny and Karen; (22 * 20 + 20 * 20 + 25 * 15)/3 = 405",
        "difficulty": 1
      }
    ]
  },

  {
    "text": "What average tax rate does Olivia have to pay on her weekly income?",
        "type": "Multiple Choice",
        "options": [
          "14.8%",
          "15.0%",
          "15.2%",
          "15.4%"
        ],
        "answer": "C",
        "explanation": "35 * 30 = 1050; (500 * 0.1 + 550 * 0.2)/1050 = 0.152",
        "difficulty": 1
      }
    ]
  },

  {
    "text": "If Penelope and Violet both decided to reduce their number of working hours (per week) by 25%, what would be the effect on the range of incomes of the group of 11 friends (per week)?",
        "type": "Multiple Choice",
        "options": [
          "$20 decrease",
          "$40 decrease",
          "$60 decrease",
          "$80 decrease"
        ],
        "answer": "A",
        "explanation": "Ralph then becomes the highest earner; 45 * 35 = 1575; 40 * 40 – 1575 = 25; 25 * 0.8 = 20",

        "difficulty": 1
      }
    ]
  },

  {
    "text": "The following table compares the average maximum and minimum temperatures (from January to December 2019) in a city. All temperatures are given in Fahrenheit. To convert from Fahrenheit to degrees Celsius, subtract 32 and multiply by 5/9.",
    "image": "https://in2med.com.au/wp-content/uploads/2021/01/Question Images (Upload)/QR Images/Questions/Centre & Spread/Batch 2 (Sahil)/9.JPG",
    "category_id": 11,
    "questions": [

  {
    "text": "What percentage of the 12 months in 2019 had an average minimum temperature below freezing (0 degrees Celsius)?",
        "type": "Multiple Choice",
        "options": [
          "33.3%",
          "41.7%",
          "50.0%",
          "58.3%"
        ],
        "answer": "B",
        "explanation": "5 months showed an average minimum temperature of below 32F",
        "difficulty": 1
      }
    ]
  },

  {
    "text": "What was the average difference in maximum and minimum temperatures in the city over the 12 months of 2019 (to the nearest degrees Fahrenheit)?",
        "type": "Multiple Choice",
        "options": [
          "16",
          "18",
          "20",
          "22"
        ],
        "answer": "C",
        "explanation": "(Sum of high – sum of low)/12 = 20",
        "difficulty": 1
      }
    ]
  },

  {
    "text": "Due to the effects of global warming, the average maximum temperature in January has been increasing by 10% (year-on-year) since 2015. What was the average maximum January temperature from 2015 to 2019 inclusive (in degrees Fahrenheit)?",
        "type": "Multiple Choice",
        "options": [
          "23.2",
          "23.6",
          "24.0",
          "24.2"
        ],
        "answer": "D",
        "explanation": "(29 + 29/1.1 + 29/(1.1^2)…+ 29/(1.1^4))/5 = 24.2",
        "difficulty": 1
      }
    ]
  },

  {
    "text": "Suppose that the minimum/maximum temperatures are recorded every day of a month and the values are averaged to give the values in the table above. In February 2019, a minimum temperature of 5 degrees Fahrenheit was recorded on 3 separate occasions. If these 3 minimums were not included in the calculations of an average, how much would the calculated average minimum temperature in February increase by (in degrees Fahrenheit)?",
        "type": "Multiple Choice",
        "options": [
          "0.4",
          "0.8",
          "1.2",
          "1.6"
        ],
        "answer": "C",
        "explanation": "(15 * 12 – 3 * 5)/9 = 15.2; 15.2 – 14 = 1.2",

        "difficulty": 1
      }
    ]
  },

  {
    "text": "The table below compares the number of customer visits and the number of orders placed on cars at a car dealership each month in 2018. To place an order on a car, the customer must visit the car dealership, place an order and pay for the car on the same day as the visit. Each car is sold by the dealership for $5000 and costs the dealership $1170 to source. The dealership’s revenue on each car is the difference between the sale price and the cost associated with sourcing the car. The dealership’s only source of revenue is selling cars.",
    "image": "https://in2med.com.au/wp-content/uploads/2021/01/Question Images (Upload)/QR Images/Questions/Centre & Spread/Batch 2 (Sahil)/10.JPG",
    "category_id": 11,
    "questions": [

  {
    "text": "What was the average number of customer visits to the dealership (each month) for 2018?",
        "type": "Multiple Choice",
        "options": [
          "2175",
          "2198",
          "2236",
          "2264"
        ],
        "answer": "D",
        "explanation": "Sum of visits/12 = 2264",
        "difficulty": 1
      }
    ]
  },

  {
    "text": "What was the car dealership’s average monthly revenue for the first quarter of 2018 (i.e from January to March) to the nearest $1000?",
        "type": "Multiple Choice",
        "options": [
          "$815000",
          "$816000",
          "$817000",
          "$818000"
        ],
        "answer": "B",
        "explanation": "(243 + 201 + 195) * (5000 – 1170) = 816000",
        "difficulty": 1
      }
    ]
  },

  {
    "text": "In which quarter of 2018 did the car dealership have the highest average monthly revenue?",
        "type": "Multiple Choice",
        "options": [
          "Quarter 1",
          "Quarter 2",
          "Quarter 3",
          "Quarter 4"
        ],
        "answer": "C",
        "explanation": "The most cars were sold from July to September",
        "difficulty": 1
      }
    ]
  },

  {
    "text": "30% of the dealership’s monthly revenue is paid to the tax office and the remaining money is paid to the staff. If there were 60 staff members in November 2018 (as opposed to 70 staff members in December 2018) how much more money was paid to each staff member, on average, in November compared to December? ",
        "type": "Multiple Choice",
        "options": [
          "$2116",
          "$2216",
          "$2316",
          "$2416"
        ],
        "answer": "B",
        "explanation": "207 * (5000 – 1170) * 0.7/60 – 201 * (5000 – 1170) * 0.7/70 = 2216",

        "difficulty": 1
      }
    ]
  },

  {
    "text": "Jim started a company that sells computers. The following table compares the number of computer sales each month for the first half of 2018 (by Jim’s company) with 2 different models used to predict the number of computer sales each month (forecast 1 and 2). Jim is trying to decide which model is more accurate in predicting his company’s monthly computer sales.",
    "image": "https://in2med.com.au/wp-content/uploads/2021/01/Question Images (Upload)/QR Images/Questions/Centre & Spread/Batch 2 (Sahil)/11.JPG",
    "category_id": 11,
    "questions": [

  {
    "text": "What was the average number of monthly sales for the first half of 2018?",
        "type": "Multiple Choice",
        "options": [
          "35",
          "39",
          "42",
          "51"
        ],
        "answer": "C",
        "explanation": "Sum of sales/6 = 42",
        "difficulty": 1
      }
    ]
  },

  {
    "text": "What percentage higher was the average monthly sales prediction for forecast 2 than the average monthly sales prediction for forecast 1? ",
        "type": "Multiple Choice",
        "options": [
          "0.83%",
          "1.05%",
          "1.83%",
          "2.05%"
        ],
        "answer": "D",
        "explanation": "((Sum of forecast 2) – (Sum of forecast 1))/(Sum of forecast 1)",
        "difficulty": 1
      }
    ]
  },

  {
    "text": "In what month was the number of computer sales equal to the average value of forecasts 1 and 2?",
        "type": "Multiple Choice",
        "options": [
          "February",
          "March",
          "April",
          "May"
        ],
        "answer": "B",
        "explanation": "The average of the forecasts equalled: (43 + 35)/2 = 39",
        "difficulty": 1
      }
    ]
  },

  {
    "text": "For July 2018, the sales prediction for forecast 1 was 6% higher than forecast 2.  The actual sales value (for July 2018) was 1% higher than the average of forecast 1 and 2. If the sales prediction for forecast 1 was 1 greater than the actual number of sales, what was the actual number of sales for July (to the nearest whole number)?",
        "type": "Multiple Choice",
        "options": [
          "50",
          "51",
          "52",
          "53"
        ],
        "answer": "D",
        "explanation": "The best way to attempt this is through a trial an error approach of each option to see which leads closest to the prediction for forecast 1 being 1 greater than the actual number of sales",

        "difficulty": 1
      }
    ]
  },

  {
    "text": "The following table compares the number of monthly influenza deaths from 1917 to 1921 in the state of Indiana.",
    "image": "https://in2med.com.au/wp-content/uploads/2021/01/Question Images (Upload)/QR Images/Questions/Centre & Spread/Batch 2 (Sahil)/12.JPG",
    "category_id": 11,
    "questions": [

  {
    "text": "What was the average number of influenza deaths (per month) in Indiana in 1921?",
        "type": "Multiple Choice",
        "options": [
          "23",
          "26",
          "29",
          "32"
        ],
        "answer": "B",
        "explanation": "Sum of the column/number of entries = 26",
        "difficulty": 1
      }
    ]
  },

  {
    "text": "In which year was the average number of influenza deaths (per month) in Indiana the highest?",
        "type": "Multiple Choice",
        "options": [
          "1917",
          "1918",
          "1919",
          "1920"
        ],
        "answer": "B",
        "explanation": "Can attempt to calculate the averages or just inspect the data to save time",
        "difficulty": 1
      }
    ]
  },

  {
    "text": "If 500 individuals died immediately (within a day) of contracting influenza in Indiana in 1919 and the immediate death rate remained consistent throughout the year, roughly how many individuals immediately died of influenza in Indiana in the first quarter of 1919?",
        "type": "Multiple Choice",
        "options": [
          "321",
          "375",
          "406",
          "414"
        ],
        "answer": "D",
        "explanation": "500/total deaths in Indiana in 1919 = 0.17; 0.17 * sum of deaths from Jan – March = 414",
        "difficulty": 1
      }
    ]
  },

  {
    "text": "If the percentage decrease in the average number of influenza deaths (per month) in Indiana from 1920 to 1921 equalled that of 1921 to 1922, how many individuals died of influenza per month (on average) in 1922 in Indiana?",
        "type": "Multiple Choice",
        "options": [
          "3.5",
          "4",
          "4.5",
          "5"
        ],
        "answer": "A",
        "explanation": "(Average number of influenza deaths in 1920 – average number of influenza deaths in 1921)/(average number of influenza deaths in 1920) * (average number of influenza deaths in 1921) = 3.5",

        "difficulty": 1
      }
    ]
  },

  {
    "text": "A group of individuals (from a variety of different age groups) were asked to choose their favourite leisure activity from a list of 6 different activities. All those surveyed made a selection and the results were tabulated.",
    "image": "https://in2med.com.au/wp-content/uploads/2021/01/Question Images (Upload)/QR Images/Questions/Centre & Spread/Batch 2 (Sahil)/13.JPG",
    "category_id": 11,
    "questions": [

  {
    "text": "What was the average number of respondents (per age group above) who chose ‘socialising with 4 or less people’ as their favourite leisure activity? ",
        "type": "Multiple Choice",
        "options": [
          "208",
          "214",
          "220",
          "226"
        ],
        "answer": "B",
        "explanation": "Sum of all figures in the row/7 = 214",
        "difficulty": 1
      }
    ]
  },

  {
    "text": "If X teens changed their selection from individual exercise to group exercise, the average number of respondents (per age group above) who chose ‘group exercise/sport’ as their favourite leisure activity would increase by approximately 7.1%. What is the value of X?",
        "type": "Multiple Choice",
        "options": [
          "65",
          "75",
          "85",
          "95"
        ],
        "answer": "C",
        "explanation": "(Total number of respondents who chose ‘group exercise/sport’) * 1.071 – Total number of respondents who chose ‘group exercise/sport’ = 85",
        "difficulty": 1
      }
    ]
  },

  {
    "text": "What leisure activity had the highest average number of respondents per age group?",
        "type": "Multiple Choice",
        "options": [
          "Watching TV/videos",
          "Socialising with 4 or less people",
          "Socialising with 4 or more people",
          "Individual exercise"
        ],
        "answer": "A",
        "explanation": "Don’t summate each row, just use inspection; tv is TV/videos is the only category with more than 1,000 individuals in an age range",
        "difficulty": 1
      }
    ]
  },

  {
    "text": "Suppose that (on average) 20% of those aged below 50 (whose favourite leisure activity is individual exercise) regularly swim, while 45% of those aged above 50 (whose favourite leisure activity is individual exercise) regularly swim. What percentage of respondents (whose favourite leisure activity is individual exercise) regularly swim?",
        "type": "Multiple Choice",
        "options": [
          "26.3%",
          "27.4%",
          "28.5%",
          "29.6%"
        ],
        "answer": "B",
        "explanation": "(650 * 0.2 + 275 * 0.45)/925 * 100 = 27.4",

        "difficulty": 1
      }
    ]
  },

  {
    "text": "The following 2 tables compare the sales (in millions of Euros) of coffee and bananas in 5 different European countries in 1999 and 2004.",
    "image": "https://in2med.com.au/wp-content/uploads/2021/01/Question Images (Upload)/QR Images/Questions/Centre & Spread/Batch 2 (Sahil)/14.JPG",
    "category_id": 11,
    "questions": [

  {
    "text": "If 1 euro is equal to 0.91 pounds, what was the average sales of coffee in the 5 countries in 1999 (in millions of pounds)?",
        "type": "Multiple Choice",
        "options": [
          "1.47",
          "1.62",
          "1.78",
          "1.94"
        ],
        "answer": "A",
        "explanation": "Sum/5 * 0.91 = 1.47",
        "difficulty": 1
      }
    ]
  },

  {
    "text": "What was the percentage increase in the total number of banana sales in the 5 countries from 1999 to 2004?",
        "type": "Multiple Choice",
        "options": [
          "86%",
          "93%",
          "186%",
          "193%"
        ],
        "answer": "C",
        "explanation": "(Total number of banana sales in 2004 - total number of banana sales in 1999)/(total number of banana sales in 1999) * 100 = 186",
        "difficulty": 1
      }
    ]
  },

  {
    "text": "What percentage reduction in the sales of coffee in the UK in 2004 would yield a 20% decrease in the average sales of coffee in the 5 countries in 2004?",
        "type": "Multiple Choice",
        "options": [
          "29%",
          "30%",
          "31%",
          "32%"
        ],
        "answer": "C",
        "explanation": "0.2 * total coffee sales in 2004 = 6.14; 6.14/20 * 100 = 31 ",
        "difficulty": 1
      }
    ]
  },

  {
    "text": "In order to increase the sales of coffee in Denmark, the unit price of coffee is reduced by 10%. As a result, the number (not value) of sales of coffee increases by 20% from 2004 to 2005. If the value of sales is equal to the number of sales multiplied by the unit price of coffee, what would be the value of coffee sales in Denmark in 2005?",
        "type": "Multiple Choice",
        "options": [
          "1.08",
          "1.64",
          "2.16",
          "3.28"
        ],
        "answer": "C",
        "explanation": "0.9 * 1.2 * 2 = 2.16",

        "difficulty": 1
      }
    ]
  },

  {
    "text": "2 separate surveys were conducted in 1985 and 2011 to determine the average distance travelled per person per year by mode of travel. The results are displayed below.",
    "image": "https://in2med.com.au/wp-content/uploads/2021/01/Question Images (Upload)/QR Images/Questions/Centre & Spread/Batch 2 (Sahil)/15.JPG",
    "category_id": 11,
    "questions": [

  {
    "text": "What was the percentage increase in the total distance travelled per person per year from 1985 to 2000?",
        "type": "Multiple Choice",
        "options": [
          "26.8%",
          "32.4%",
          "36.6%",
          "38.2%"
        ],
        "answer": "C",
        "explanation": "(total distance travelled in 2000 – total distance travelled in 1985)/(total distance travelled in 2000) * 100 = 36.6",
        "difficulty": 1
      }
    ]
  },

  {
    "text": "Suppose that all cars require petrol. In 1985 petrol cost $1 per litre while in 2000 petrol cost $1.50 per litre. Each litre of petrol allows a car to travel to travel for 2.5 miles. How much more money was spent on average (per person per year) on petrol (for cars) in 2000 than 1985?",
        "type": "Multiple Choice",
        "options": [
          "$1280",
          "$1440",
          "$1604",
          "$2884"
        ],
        "answer": "C",
        "explanation": "4806/2.5 * 1.5 – 3199/2.5 = 1604",
        "difficulty": 1
      }
    ]
  },

  {
    "text": "If 1.6km=1 mile and walking for 1km burns 100 calories of energy, how many calories of energy did the average person burn per month (on average) from walking alone in 1985?",
        "type": "Multiple Choice",
        "options": [
          "3400",
          "3600",
          "3800",
          "4000"
        ],
        "answer": "A",
        "explanation": "255 * 100 * 1.6/12 = 3400",
        "difficulty": 1
      }
    ]
  },

  {
    "text": "Suppose that the ‘other’ modes of travel consist only of boat and tram travel and, on average individuals travel 3 times as much distance on boats than trams (each year). How much more did individuals travel (on average) by boat in 2000 than 1985 (in miles)?",
        "type": "Multiple Choice",
        "options": [
          "97.4",
          "99.6",
          "100.5",
          "101.3"
        ],
        "answer": "D",
        "explanation": "3/4 * (585 – 450) = 101.3",

        "difficulty": 1
      }
    ]
  },

  {
    "text": "The following table illustrates the 6 different types of families within country X and the number/ proportion of people from each family types living in poverty. Assume that every citizen of country X fits into one of those family types and the population of country X is 17 million.",
    "image": "https://in2med.com.au/wp-content/uploads/2021/01/Question Images (Upload)/QR Images/Questions/Centre & Spread/Batch 2 (Sahil)/16.JPG",
    "category_id": 11,
    "questions": [

  {
    "text": "On average, out of every 400 citizens of country X, how many are single aged people?",
        "type": "Multiple Choice",
        "options": [
          "12.5",
          "15.3",
          "18.4",
          "21.2"
        ],
        "answer": "D",
        "explanation": "54000/0.06=900000; 900000/1700000 * 400 = 21.2",
        "difficulty": 1
      }
    ]
  },

  {
    "text": "Approximately what percentage of citizens of country X poverty?",
        "type": "Multiple Choice",
        "options": [
          "10.3%",
          "10.8%",
          "11.7%",
          "12.6%"
        ],
        "answer": "B",
        "explanation": "Sum of third column/17 million * 100 = 10.8",
        "difficulty": 1
      }
    ]
  },

  {
    "text": "If there are 2 million households in country X consisting of couples with children, how many people (on average) occupy each of these households?",
        "type": "Multiple Choice",
        "options": [
          "3.93",
          "4.17",
          "4.56",
          "4.80"
        ],
        "answer": "A",
        "explanation": "944/0.12 = 7867; 7867/2000 = 3.94",
        "difficulty": 1
      }
    ]
  },

  {
    "text": "Each individual living in poverty from country X claims $300, $400 or $500 weekly from the governments. 40% of those living in poverty claim $500 weekly, while twice as many individuals claim $400 weekly than $300 weekly. How much does country X pay monthly (on average) to each individual living in poverty?",
        "type": "Multiple Choice",
        "options": [
          "$1530",
          "$1600",
          "$1680",
          "$1760"
        ],
        "answer": "C",
        "explanation": "(0.4 * 500 + 0.4 * 400 + 0.2 * 200) * 4 = 1680",

        "difficulty": 1
      }
    ]
  },

  {
    "text": "The table below depicts the quantities of fruit sold annually (in thousands of tonnes) in 5 different countries.",
    "image": "https://in2med.com.au/wp-content/uploads/2021/01/Question Images (Upload)/QR Images/Questions/Centre & Spread/Batch 2 (Sahil)/17.JPG",
    "category_id": 11,
    "questions": [

  {
    "text": "What is the average quantity of peaches sold in each of the 5 countries annually (in tonnes)?",
        "type": "Multiple Choice",
        "options": [
          "4500",
          "4540",
          "4600",
          "4640"
        ],
        "answer": "B",
        "explanation": "Sum of column/5 = 4540",
        "difficulty": 1
      }
    ]
  },

  {
    "text": "What percentage higher is the average quantity of Cherries sold in each of the 5 countries annually than the average quantity of oranges sold in each of the 5 countries annually?",
        "type": "Multiple Choice",
        "options": [
          "45%",
          "50%",
          "55%",
          "60%"
        ],
        "answer": "C",
        "explanation": "(Average of cherries – average of oranges)/(average of cherries) * 100 = 55%",
        "difficulty": 1
      }
    ]
  },

  {
    "text": "If 25% of the ‘others’ category consists of mandarins, how many more mandarins are sold than bananas each month (on average) in Australia?",
        "type": "Multiple Choice",
        "options": [
          "6.25 tonnes",
          "6.75 tonnes",
          "7.5 tonnes",
          "8.25 tonnes"
        ],
        "answer": "A",
        "explanation": "(0.25 * 16.3 – 4)/12 * 1000 = 6.25",
        "difficulty": 1
      }
    ]
  },

  {
    "text": "If each ton of grapes is sold for 36% more than each ton of bananas, what percentage more is generated from the sale of grapes in the UK than bananas in Italy?",
        "type": "Multiple Choice",
        "options": [
          "23.4%",
          "24.5%",
          "25.9%",
          "26.2%"
        ],
        "answer": "D",
        "explanation": "(6.5 * 1.36 – 7)/ (6.5 * 1.36) * 100 = 26.2",

        "difficulty": 1
      }
    ]
  },

  {
    "text": "The number of sales of a product within a number of stores across the cities of America, along with the unit price of the product, are illustrated in the table below.",
    "image": "https://in2med.com.au/wp-content/uploads/2021/01/Question Images (Upload)/QR Images/Questions/Centre & Spread/Batch 2 (Sahil)/18.JPG",
    "category_id": 11,
    "questions": [

  {
    "text": "What is the average quantity of the product sold in each of the stores listed?",
        "type": "Multiple Choice",
        "options": [
          "766.7",
          "789.3",
          "807.5",
          "818.1"
        ],
        "answer": "A",
        "explanation": "Sum of quantity sold column/10 = 766.7",
        "difficulty": 1
      }
    ]
  },

  {
    "text": "What would be the percentage increase in the average money generated by these stores from the sale of this product if the unit price was increased by 15%?",
        "type": "Multiple Choice",
        "options": [
          "13.3%",
          "15%",
          "16.7%",
          "20%"
        ],
        "answer": "B",
        "explanation": "A 15% increase is maintained",
        "difficulty": 1
      }
    ]
  },

  {
    "text": "If X number more products were sold at both of the Chicago stores, the average money generated by the sale of the products in the Chicago stores would be exactly three-quarters that of the St Louis stores. What is the value of X?",
        "type": "Multiple Choice",
        "options": [
          "176",
          "188",
          "352",
          "376"
        ],
        "answer": "B",
        "explanation": "0.75 * 1928 = 1446; (1446  – 1070)/2=188",
        "difficulty": 1
      }
    ]
  },

  {
    "text": "What is the minimum percentage increase required in the unit price of the product in the Seattle stores such that they generate the same money (on average) as the Los Angeles stores?",
        "type": "Multiple Choice",
        "options": [
          "28.7%",
          "29.6%",
          "31.2%",
          "32.9%"
        ],
        "answer": "D",
        "explanation": "(750 +462 – 400 – 512)/ (750 +462) * 100 = 32.9",

        "difficulty": 1
      }
    ]
  },

  {
    "text": "A survey was carried out in a primary school class to determine the number of hours spent watching TV (by students) every week. All students were required to give their answer as a whole number and all responses were between 1 and 10. The number of students are displayed on the y-axis and the number of hours are displayed on the x-axis.",
    "image": "https://in2med.com.au/wp-content/uploads/2021/01/Question Images (Upload)/QR Images/Questions/Centre & Spread/Batch 2 (Sahil)/19.JPG",
    "category_id": 11,
    "questions": [

  {
    "text": "How many students watch an average of more than 40 minutes of TV every day?",
        "type": "Multiple Choice",
        "options": [
          "22",
          "30",
          "36",
          "41"
        ],
        "answer": "B",
        "explanation": "40 * 7/60=4.7; number of students watching 5 or more hours is 30",
        "difficulty": 1
      }
    ]
  },

  {
    "text": "Experts recommend that children watch no more than an average of half an hour of TV daily. How many students in this class are not adhering to this guideline?",
        "type": "Multiple Choice",
        "options": [
          "22",
          "30",
          "36",
          "41"
        ],
        "answer": "C",
        "explanation": "0.5 * 7 = 3.5; number of students watching 4 or more hours is 30",
        "difficulty": 1
      }
    ]
  },

  {
    "text": "John, Jeff and Jill are in this class. John averages half the time watching TV each day than Jeff while Jeff averages two-thirds the time watching TV each day than Jill. If Jill spends 1 hour watching TV each day (on average), how many classmates spend the same amount of time watching TV (each week to the nearest half hour) as John?",
        "type": "Multiple Choice",
        "options": [
          "2",
          "3",
          "4 ",
          "5"
        ],
        "answer": "D",
        "explanation": "Jeff – 40 minutes; John – 20 minutes per day = 2 hrs 20 per week; 5 in the 2 hr category",
        "difficulty": 1
      }
    ]
  },

  {
    "text": "What is the average time spent by each student in this class watching TV each week (in hours)?",
        "type": "Multiple Choice",
        "options": [
          "5.0",
          "5.1",
          "5.2",
          "5.3"
        ],
        "answer": "D",
        "explanation": "Multiply each time by the number of students watching for that time and sum together, then divide by the number of students total",

        "difficulty": 1
      }
    ]
  },

  {
    "text": "Mary is looking to buy a new house. She is researching houses on sale in her desired suburb and taking note of the amenities in each house; in particular, the number of bathrooms in each house. The following table depicts the number of bathrooms and the number of houses (on sale in the suburb) with the indicated number of bathrooms.",
    "image": "https://in2med.com.au/wp-content/uploads/2021/01/Question Images (Upload)/QR Images/Questions/Centre & Spread/Batch 2 (Sahil)/20.JPG",
    "category_id": 11,
    "questions": [

  {
    "text": "If the average price of the houses with one bathroom is $250K and the two most expensive houses with one bedroom (each worth $1 million) are sold, by how much will the average house price of the houses with one bathroom decrease (to the nearest thousand dollars)?",
        "type": "Multiple Choice",
        "options": [
          "$51000",
          "$52000",
          "$53000",
          "$54000"
        ],
        "answer": "D",
        "explanation": "250000 – (250 * 30 – 2000000)/28 = 54000",
        "difficulty": 1
      }
    ]
  },

  {
    "text": "What will be the increase in the average number of bathrooms in each of the houses if the number of houses with 3 bathrooms was doubled?",
        "type": "Multiple Choice",
        "options": [
          "0.1",
          "0.2",
          "0.3",
          "Can’t tell"
        ],
        "answer": "D",
        "explanation": "The final category doesn’t give us a definite number of bathrooms",
        "difficulty": 1
      }
    ]
  },

  {
    "text": "If twice as many of the houses have 5 bathrooms than 7 bathrooms (more than 1), what is the average number of bathrooms in each of the houses?",
        "type": "Multiple Choice",
        "options": [
          "1",
          "1.5",
          "2",
          "2.5"
        ],
        "answer": "C",
        "explanation": "Multiply the number of bathrooms by the frequency and add them, divide by the total frequency",
        "difficulty": 1
      }
    ]
  },

  {
    "text": "Mary buys a house for $856K. She takes out a $700K loan and pays $156K from her savings. In order to pay off the loan, Mary plans to pay an average of $51K per year for 14 years. What percentage more would Mary be paying this way in comparison to paying the $856K directly from her savings?",
        "type": "Multiple Choice",
        "options": [
          "0.8%",
          "1.2%",
          "1.6%",
          "2.0%"
        ],
        "answer": "C",
        "explanation": "51 * 14 = 714; 14/856 * 100 = 1.6%",

        "difficulty": 1
      }
    ]
  },

  {
    "text": "The following graph shows the amount of environmental waste created and recycled from 2000 to 2013 in tonnes.",
    "image": "https://in2med.com.au/wp-content/uploads/2021/01/Question Images (Upload)/QR Images/Questions/Centre & Spread/Batch 1 (Raman)/1.JPG",
    "category_id": 11,
    "questions": [

  {
    "text": "What is the closest average of the total waste generated from 2000, 2005 and 2007?",
        "type": "Multiple Choice",
        "options": [
          "2 million tonnes",
          "2.5 million tonnes",
          "3 million tonnes",
          "Can’t tell"
        ],
        "answer": "B",
        "explanation": "(1.9 + 2.6 + 3)/3 = 2.5",
        "difficulty": 1
      }
    ]
  },

  {
    "text": "If the total waste generated in 2009 was 3.15 million tonnes, what is the average of total waste generated from 2007-2010?",
        "type": "Multiple Choice",
        "options": [
          "3.10 million",
          "3.13 million",
          "3.15 million",
          "Can’t tell "
        ],
        "answer": "D",
        "explanation": "No statistic is given for 2008",
        "difficulty": 1
      }
    ]
  },

  {
    "text": "Which pairs of years had the same average of trashed waste?",
        "type": "Multiple Choice",
        "options": [
          "2005/2007 and 2009/2010",
          "2005/2007 and 2011/2012",
          "2009/2010 and 2011/2012",
          "2009/2010 and 2012/2013"
        ],
        "answer": "C",
        "explanation": "2009/2010 and 2011/2012; average of ~3.25 million tonnes",
        "difficulty": 1
      }
    ]
  },

  {
    "text": "In which year was the average of trashed and recycled waste equal to 1.5 million?",
        "type": "Multiple Choice",
        "options": [
          "2000",
          "2007",
          "2010",
          "2013"
        ],
        "answer": "B",
        "explanation": "Total waste would be 1.5 * 2 =3; This is seen in 2007",

        "difficulty": 1
      }
    ]
  },

  {
    "text": "The following graph displays the preferred snack choices of students at Hillary’s high school, for both boys and girls.",
    "image": "https://in2med.com.au/wp-content/uploads/2021/01/Question Images (Upload)/QR Images/Questions/Centre & Spread/Batch 1 (Raman)/2.JPG",
    "category_id": 11,
    "questions": [

  {
    "text": "What is the closest average number of boys who preferred snacks starting with a P or V?",
        "type": "Multiple Choice",
        "options": [
          "120 students",
          "160 students",
          "220 students",
          "280 students"
        ],
        "answer": "B",
        "explanation": "(180 + 170 + 130)/3 = 160",
        "difficulty": 1
      }
    ]
  },

  {
    "text": "Which of the following snack choice has the highest preference numbers as an average of girls and boys? ",
        "type": "Multiple Choice",
        "options": [
          "Candy",
          "Popcorn",
          "Fruit",
          "Crackers"
        ],
        "answer": "C",
        "explanation": "The highest of the following is fruit (being ~185); The highest overall would be chips",
        "difficulty": 1
      }
    ]
  },

  {
    "text": "Which snack choice has the lowest preference numbers as an average of boys and girls?",
        "type": "Multiple Choice",
        "options": [
          "Vegetables",
          "Pretzels",
          "Popcorn",
          "Ice cream"
        ],
        "answer": "A",
        "explanation": "Vegetable only has an average of ~155; This can be answered via inspection to save time",
        "difficulty": 1
      }
    ]
  },

  {
    "text": "What is the difference between the average number of boys who preferred popcorn and chocolate bars compared to the average number of girls who preferred popcorn and candy, to the closest value?",
        "type": "Multiple Choice",
        "options": [
          "20 students",
          "28 students",
          "32 students",
          "36 students"
        ],
        "answer": "B",
        "explanation": "((175 + 255) – (175 + 200))/2 = ~28",

        "difficulty": 1
      }
    ]
  },

  {
    "text": "The following graph shows the rates of unemployment for adults in the Nordic countries for men and women. The total population of Denmark is 10 million, Finland is 15 million, Iceland is 20 million, Norway is 25 million and Sweden is 30 million. Assume there are the same number of men and women in each country",
    "image": "https://in2med.com.au/wp-content/uploads/2021/01/Question Images (Upload)/QR Images/Questions/Centre & Spread/Batch Batch 1 (Raman)/3.JPG",
    "category_id": 11,
    "questions": [

  {
    "text": "What is the average unemployment rate amongst men in Denmark and Finland collectively?",
        "type": "Multiple Choice",
        "options": [
          "4%",
          "4.5%",
          "5%",
          "5.5%"
        ],
        "answer": "C",
        "explanation": "(0.03 * 10 + 0.06 * 15)/25 * 100 = ~5% ",
        "difficulty": 1
      }
    ]
  },

  {
    "text": "What is the average difference between the number of unemployed women and men of the two countries, Denmark and Iceland?",
        "type": "Multiple Choice",
        "options": [
          "60,000",
          "70,000",
          "90,000 ",
          "110,000"
        ],
        "answer": "D",
        "explanation": "(0.007 * 10 + 0.008 * 20)/2 = ~0.11 (million)",
        "difficulty": 1
      }
    ]
  },

  {
    "text": "What is the average difference in male and female unemployment rates across all 5 countries?",
        "type": "Multiple Choice",
        "options": [
          "0.52%",
          "0.62%",
          "0.72%",
          "0.82%"
        ],
        "answer": "B",
        "explanation": "Sum of male unemployment rates/5 – sum of female unemployment rates/5 = 0.62",
        "difficulty": 1
      }
    ]
  },

  {
    "text": "If the average unemployment rate was 5% in Norway last year, by how much has the current average unemployment rate for in Norway changed?",
        "type": "Multiple Choice",
        "options": [
          "-2.45%",
          "+2.45%",
          "-2.55%",
          "+2.55"
        ],
        "answer": "A",
        "explanation": "(2.7 + 2.4)/2 =2.55; 2.55 – 5 = -2.45",

        "difficulty": 1
      }
    ]
  },

  {
    "text": "The following graph shows the number of sneakers sold this month in Chadstone Shopping Centre.",
    "image": "https://in2med.com.au/wp-content/uploads/2021/01/Question Images (Upload)/QR Images/Questions/Centre & Spread/Batch 1 (Raman)/4.JPG",
    "category_id": 11,
    "questions": [

  {
    "text": "What is the average number of sneakers sold this month at Chadstone Shopping Centre?",
        "type": "Multiple Choice",
        "options": [
          "15 sneakers",
          "20 sneakers",
          "25 sneakers",
          "30 sneakers"
        ],
        "answer": "B",
        "explanation": "Sum of sales/5 = 20",
        "difficulty": 1
      }
    ]
  },

  {
    "text": "If the average number of sneakers sold this month at Chadstone Shopping Centre was 25 sneakers, including a new Bomber sneaker that is not accounted for in the graph, how many Bomber sneakers were sold this month at Chadstone Shopping Centre?",
        "type": "Multiple Choice",
        "options": [
          "20",
          "30",
          "40",
          "50"
        ],
        "answer": "D",
        "explanation": "25 * 6 – 100 = 50",
        "difficulty": 1
      }
    ]
  },

  {
    "text": "What is the average number of sneakers sold this month at Chadstone Shopping Centre, of those which sold over 15 sneakers?",
        "type": "Multiple Choice",
        "options": [
          "22",
          "22.5",
          "23",
          "25"
        ],
        "answer": "D",
        "explanation": "(25 + 18 + 32)/3 = 25",
        "difficulty": 1
      }
    ]
  },

  {
    "text": "If the number of New Balance sneakers sold was actually 28, but how much does the average of sneakers sold at Chadstone Shopping Centre change?",
        "type": "Multiple Choice",
        "options": [
          "Increase by 2",
          "Decrease by 2",
          "Increase by 10",
          "Decrease by 10"
        ],
        "answer": "A",
        "explanation": "(28 – 18)/5 = 2",

        "difficulty": 1
      }
    ]
  },

  {
    "text": "The following chart displays the trends in overweight and obese people from 1997-2007 in America vs the state of Wisconsin, as a percentage of the total population. ",
    "image": "https://in2med.com.au/wp-content/uploads/2021/01/Question Images (Upload)/QR Images/Questions/Centre & Spread/Batch 1 (Raman)/5.JPG",
    "category_id": 11,
    "questions": [
  {
    "text": "If the population of the nation in 2003 and 2001 was 200 million and 150 million respectively, what is the average number of obese people in the nation between 2001 and 2003 on the graph (not including 2002), to the nearest million?",
        "type": "Multiple Choice",
        "options": [
          "19 million",
          "20 million",
          "21 million",
          "22 million",
        ],
        "answer": "B",
        "explanation": "200 million * 0.12 = 24 million<br/>150 million * 0.105 = 15.75 million<br/>(24 million + 15.57 million)/2 = 19.875 million = 20 million to the nearest million",
        "difficulty": 1
      }
    ]
  },

  {
    "text": "What is the average number of obese and overweight people combined, between the nation and Wisconsin in 2007, to the nearest ten? The population of the nation in 2007 was 300 million, and in Wisconsin 56 million.",
        "type": "Multiple Choice",
        "options": [
          "40 million",
          "50 million",
          "60 million",
          "80 million"
        ],
        "answer": "B",
        "explanation": "(0.281 * 300 + 0.251 * 56)/2 = 50",
        "difficulty": 1
      }
    ]
  },

  {
    "text": "If the average percentage of overweight people in the nation over the years, 1999, 2001, 2003, 2005 and 2007 was 14.78%, what was the percentage of overweight people in the nation in 1999?",
        "type": "Multiple Choice",
        "options": [
          "13.5%",
          "14%",
          "14.5%",
          "15%"
        ],
        "answer": "C",
        "explanation": "14.78 * 5 – percentage overweight in 2001, 2003, 2005 and 2007 = 14.5",
        "difficulty": 1
      }
    ]
  },

  {
    "text": "If the average number of overweight and obese people in the nation in 2003 and 2007 was 100 million, and there were 150 million overweight and obese people people in the nation in 2003, how many overweight and obese people were in the nation in 2007?",
        "type": "Multiple Choice",
        "options": [
          "50 million",
          "100 million",
          "150 million",
          "200 million "
        ],
        "answer": "A",
        "explanation": "2*100 – 150 = 50 (million)",

        "difficulty": 1
      }
    ]
  },

  {
    "text": "The following table shows the transmission of light through a beaker of water with varying salt concentrations over 5 trials. ",
    "image": "https://in2med.com.au/wp-content/uploads/2021/01/Question Images (Upload)/QR Images/Questions/Centre & Spread/Batch 1 (Raman)/6.JPG",
    "category_id": 11,
    "questions": [

  {
    "text": "What is the average transmittance across all 5 trials at a salt concentration of 12%, to 2 decimal places?",
        "type": "Multiple Choice",
        "options": [
          "74.94%",
          "74.49%",
          "75.02%",
          "75.01%"
        ],
        "answer": "A",
        "explanation": "Sum of row/5 = 74.94",
        "difficulty": 1
      }
    ]
  },

  {
    "text": "What is the average difference between the transmittance recordings between trials of the same number at salt concentrations of 6% and 9%?",
        "type": "Multiple Choice",
        "options": [
          "5.2460%",
          "6.5575%",
          "7.6800%",
          "11.580%"
        ],
        "answer": "A",
        "explanation": "Difference of each trial (higher value – lower value) added together and divided by 5 will give 5.2460%",
        "difficulty": 1
      }
    ]
  },

  {
    "text": "If the average transmittance across all salt concentrations for Trial 2 was 100%, what is the transmittance for Trial 2 at a salt concentration of 3%?",
        "type": "Multiple Choice",
        "options": [
          "92.72%",
          "92.82%",
          "92.92%",
          "100.0%"
        ],
        "answer": "B",
        "explanation": "100 * 5 – the sum of the values of the four other trials = 92.82",
        "difficulty": 1
      }
    ]
  },

  {
    "text": "Which salt concentration out of the following had the lowest average transmittance across Trials 1, 3, 4 and 5?",
        "type": "Multiple Choice",
        "options": [
          "0%",
          "6%",
          "9%",
          "12%"
        ],
        "answer": "C",
        "explanation": "You can calculate the average transmittance by summing the trials and dividing the value by 5 for all the different salt concentrations. Or you can attempt to arrive at 9% via inspection",

        "difficulty": 1
      }
    ]
  },

  {
    "text": "The following table below shows the GDP of 5 countries from 1998 to 2003. The values are in billions of dollars.",
    "image": "https://in2med.com.au/wp-content/uploads/2021/01/Question Images (Upload)/QR Images/Questions/Centre & Spread/Batch 1 (Raman)/7.JPG",
    "category_id": 11,
    "questions": [

  {
    "text": "What was average GDP for China from 1998 to 2003, in billions of dollars to the nearest billion?",
        "type": "Multiple Choice",
        "options": [
          "1,318",
          "1,319",
          "1,320",
          "1,321"
        ],
        "answer": "B",
        "explanation": "Sum of row/6 = 1319",
        "difficulty": 1
      }
    ]
  },

  {
    "text": "If the exchange rate from dollars to rupees (Indian currency) is 150 (1 dollar is 150 rupees), what is the average GDP for India between 2001 and 2003 in billions of rupees?",
        "type": "Multiple Choice",
        "options": [
          "74,900",
          "79,400",
          "529.33",
          "530"
        ],
        "answer": "B",
        "explanation": "(599 + 510 + 479)/3 * 150 = 79400",
        "difficulty": 1
      }
    ]
  },

  {
    "text": "Of these 5 countries, what was the average GDP in 1999?",
        "type": "Multiple Choice",
        "options": [
          "4,228.6 billion dollars",
          "4,235.8 billion dollars",
          "4,064.2 billion dollars",
          "4,101.4 billion dollars"
        ],
        "answer": "B",
        "explanation": "Sum of column/5 = 4,235.8",
        "difficulty": 1
      }
    ]
  },

  {
    "text": "Of the following years, which year had the lowest average GDP across the 5 countries?",
        "type": "Multiple Choice",
        "options": [
          "1999",
          "2000",
          "2001",
          "2002"
        ],
        "answer": "B",
        "explanation": "Can attempt to compare average GDPs for the years by calculating: Sum of column/5; Or, you could seek to answer the this via inspection",

        "difficulty": 1
      }
    ]
  },

  {
    "text": "The following table shows the different prices in dollars and mileage in kilometers for two different models of Chevrolet cars.",
    "image": "https://in2med.com.au/wp-content/uploads/2021/01/Question Images (Upload)/QR Images/Questions/Centre & Spread/Batch 1 (Raman)/8.JPG",
    "category_id": 11,
    "questions": [

  {
    "text": "What is the average price for Corvette models in dollars?",
        "type": "Multiple Choice",
        "options": [
          "35,821.4",
          "36,821.4",
          "37,214.1",
          "38,214.1"
        ],
        "answer": "B",
        "explanation": "Sum of Corvette prices/4 = 36,821.4",
        "difficulty": 1
      }
    ]
  },

  {
    "text": "What is the difference between the average mileage of Corvette models and Malibu models?",
        "type": "Multiple Choice",
        "options": [
          "7,425.28",
          "7,915.40",
          "8,910.33",
          "8955.99"
        ],
        "answer": "C",
        "explanation": "Sum of Corvette milages/4 – sum of Malibu milages/4 = 8,910.33",
        "difficulty": 1
      }
    ]
  },

  {
    "text": "If the average price in dollars for Malibu models is $34,676.83, what is the value of the black space in the table, to the nearest dollar?",
        "type": "Multiple Choice",
        "options": [
          "$28,845",
          "$28,846",
          "$28,847",
          "$28,848"
        ],
        "answer": "B",
        "explanation": "34,676.83 * 6 – the 5 existing Malibu prices = 28,846",
        "difficulty": 1
      }
    ]
  },

  {
    "text": "What is the average mileage between the most expensive Malibu model and the cheapest Corvette model (excluding the blank value)?",
        "type": "Multiple Choice",
        "options": [
          "52,902.5km",
          "46,805.0km",
          "36,332.5km",
          "72,665.0km"
        ],
        "answer": "C",
        "explanation": "(467000 + 25965)/2 = 36,332.5",


        "difficulty": 1
      }
    ]
  },

  {
    "text": "The table below shows the different times it took for 3 different hamsters to complete a maze designed by some scientists. Each of the hamsters had 10 attempts at completing the maze and all of them completed it.",
    "image": "https://in2med.com.au/wp-content/uploads/2021/01/Question Images (Upload)/QR Images/Questions/Centre & Spread/Batch 1 (Raman)/9.JPG",
    "category_id": 11,
    "questions": [

  {
    "text": "What was the average time taken by hamster 1 to complete the maze in the first 6 trials, rounded to the nearest second?",
        "type": "Multiple Choice",
        "options": [
          "37 seconds",
          "38 seconds",
          "39 seconds",
          "40 seconds"
        ],
        "answer": "A",
        "explanation": "Sum of column for hamster 1/6 = 37",
        "difficulty": 1
      }
    ]
  },

  {
    "text": "What was the average time for all 3 hamsters in the 7th attempt?",
        "type": "Multiple Choice",
        "options": [
          "27 seconds",
          "28 seconds",
          "29 seconds",
          "27.5 seconds"
        ],
        "answer": "B",
        "explanation": "(27 + 28 + 29)/3 =28",
        "difficulty": 1
      }
    ]
  },

  {
    "text": "If a 4th hamster was included in the table, what would its time to complete the maze have been for attempt 4 if the average time for all 4 hamsters on attempt 4 was 37.5 seconds?",
        "type": "Multiple Choice",
        "options": [
          "39 seconds",
          "38 seconds",
          "37 seconds",
          "36 seconds"
        ],
        "answer": "A",
        "explanation": "37.5 * 4 – 34 – 37 – 40 = 39",
        "difficulty": 1
      }
    ]
  },

  {
    "text": "What is the difference in the average time taken to the complete the maze across all 10 attempts for hamster 3 and hamster 2?",
        "type": "Multiple Choice",
        "options": [
          "3.0 seconds",
          "3.1 seconds",
          "3.2 seconds",
          "3.3 seconds"
        ],
        "answer": "B",
        "explanation": "Sum of column for hamster 3/10 – sum of column for hamster 2/10  = 3.1; if you get a negative answer, take the magnitude of that as your answer",


        "difficulty": 1
      }
    ]
  },

  {
    "text": "The table below shows the different times it took for 3 different mice to complete a maze designed by some scientists. Each of the mice had 10 attempts at completing the maze and all of them completed it. Some of the values are missing.",
    "image": "https://in2med.com.au/wp-content/uploads/2021/01/Question Images (Upload)/QR Images/Questions/Centre & Spread/Batch 1 (Raman)/10.JPG",
    "category_id": 11,
    "questions": [

  {
    "text": "What was the average time taken to complete the maze on attempt 5 by all 3 mice?",
        "type": "Multiple Choice",
        "options": [
          "25 seconds",
          "27 seconds",
          "27.5 seconds",
          "29 seconds"
        ],
        "answer": "B",
        "explanation": "(29 + 27 + 25)/3 = 27",
        "difficulty": 1
      }
    ]
  },

  {
    "text": "How much longer/shorter did mouse 3 take to complete the maze on the 8th attempt than mouse 2?",
        "type": "Multiple Choice",
        "options": [
          "2 seconds",
          "4 seconds ",
          "22 seconds",
          "20 seconds"
        ],
        "answer": "A",
        "explanation": "22 – 20 = 2",
        "difficulty": 1
      }
    ]
  },

  {
    "text": "If the average time of all 3 mice on attempt 7 is 24, how long did mouse 2 take in attempt 7?",
        "type": "Multiple Choice",
        "options": [
          "24 seconds",
          "23 seconds",
          "22 seconds",
          "30 seconds"
        ],
        "answer": "A",
        "explanation": "24 * 3 – 25 – 23 = 24",
        "difficulty": 1
      }
    ]
  },

  {
    "text": "What was the average time of mouse 3 to complete the maze across all its 10 attempts?",
        "type": "Multiple Choice",
        "options": [
          "25.9 seconds",
          "26.2 seconds",
          "29.1 seconds",
          "30.2 seconds"
        ],
        "answer": "B",
        "explanation": "Sum of mouse 3 column/10 = 26.2",
        "difficulty": 1
      }
    ]
  },


    ]
  }